MANIFEST.in
README.markdown
setup.py
django_admin_filtrate.egg-info/PKG-INFO
django_admin_filtrate.egg-info/SOURCES.txt
django_admin_filtrate.egg-info/dependency_links.txt
django_admin_filtrate.egg-info/top_level.txt
filtrate/__init__.py
filtrate/filters.py
filtrate/settings.py
filtrate/static/filtrate/css/filtrate.css
filtrate/static/filtrate/js/daterangefilter.js
filtrate/static/filtrate/js/filtertree.js
filtrate/static/filtrate/js/filtrate.js
filtrate/static/filtrate/js/jstree/jquery.jstree.js
filtrate/static/filtrate/js/jstree/_demo/file.png
filtrate/static/filtrate/js/jstree/_demo/folder.png
filtrate/static/filtrate/js/jstree/_demo/index.html
filtrate/static/filtrate/js/jstree/_demo/root.png
filtrate/static/filtrate/js/jstree/_docs/!style.css
filtrate/static/filtrate/js/jstree/_docs/_drive.png
filtrate/static/filtrate/js/jstree/_docs/_html_data.html
filtrate/static/filtrate/js/jstree/_docs/checkbox.html
filtrate/static/filtrate/js/jstree/_docs/contextmenu.html
filtrate/static/filtrate/js/jstree/_docs/cookies.html
filtrate/static/filtrate/js/jstree/_docs/core.html
filtrate/static/filtrate/js/jstree/_docs/crrm.html
filtrate/static/filtrate/js/jstree/_docs/dnd.html
filtrate/static/filtrate/js/jstree/_docs/hotkeys.html
filtrate/static/filtrate/js/jstree/_docs/html_data.html
filtrate/static/filtrate/js/jstree/_docs/index.html
filtrate/static/filtrate/js/jstree/_docs/json_data.html
filtrate/static/filtrate/js/jstree/_docs/languages.html
filtrate/static/filtrate/js/jstree/_docs/logo.png
filtrate/static/filtrate/js/jstree/_docs/search.html
filtrate/static/filtrate/js/jstree/_docs/sort.html
filtrate/static/filtrate/js/jstree/_docs/themeroller.html
filtrate/static/filtrate/js/jstree/_docs/themes.html
filtrate/static/filtrate/js/jstree/_docs/types.html
filtrate/static/filtrate/js/jstree/_docs/ui.html
filtrate/static/filtrate/js/jstree/_docs/unique.html
filtrate/static/filtrate/js/jstree/_docs/xml_data.html
filtrate/static/filtrate/js/jstree/_docs/syntax/!script.js
filtrate/static/filtrate/js/jstree/_docs/syntax/!style.css
filtrate/static/filtrate/js/jstree/_docs/syntax/help.png
filtrate/static/filtrate/js/jstree/_docs/syntax/magnifier.png
