Metadata-Version: 1.0
Name: django-admin-filtrate
Version: 0.1.0
Summary: This Django app makes it easier to create custom filters in the change list of Django Admin and supplies a TreeFilter and a DateRangeFilter too.
Home-page: https://github.com/runekaagaard/django-admin-filtrate
Author: Rune Kaagaard
Author-email: rumi.kg@gmail.com
License: MIT
Platform: UNKNOWN
